ckanext/__init__.py
ckanext/search_tweaks/__init__.py
ckanext/search_tweaks/cli.py
ckanext/search_tweaks/config.py
ckanext/search_tweaks/config_declaration.yaml
ckanext/search_tweaks/interfaces.py
ckanext/search_tweaks/plugin.py
ckanext/search_tweaks/shared.py
ckanext/search_tweaks/advanced_search/__init__.py
ckanext/search_tweaks/advanced_search/plugin.py
ckanext/search_tweaks/advanced_search/assets/advanced-search.css
ckanext/search_tweaks/advanced_search/assets/advanced-search.js
ckanext/search_tweaks/advanced_search/assets/webassets.yml
ckanext/search_tweaks/advanced_search/templates/advanced_search/search_form.html
ckanext/search_tweaks/field_relevance/__init__.py
ckanext/search_tweaks/field_relevance/plugin.py
ckanext/search_tweaks/field_relevance/views.py
ckanext/search_tweaks/field_relevance/assets/search-tweaks-reflect-range-in-label.js
ckanext/search_tweaks/field_relevance/assets/webassets.yml
ckanext/search_tweaks/field_relevance/templates/search_tweaks/field_relevance/promote.html
ckanext/search_tweaks/query_popularity/__init__.py
ckanext/search_tweaks/query_popularity/config.py
ckanext/search_tweaks/query_popularity/config_declaration.yaml
ckanext/search_tweaks/query_popularity/plugin.py
ckanext/search_tweaks/query_popularity/score.py
ckanext/search_tweaks/query_popularity/logic/__init__.py
ckanext/search_tweaks/query_popularity/logic/action.py
ckanext/search_tweaks/query_popularity/logic/auth.py
ckanext/search_tweaks/query_popularity/logic/schema.py
ckanext/search_tweaks/query_relevance/__init__.py
ckanext/search_tweaks/query_relevance/boost.py
ckanext/search_tweaks/query_relevance/cli.py
ckanext/search_tweaks/query_relevance/config.py
ckanext/search_tweaks/query_relevance/config_declaration.yaml
ckanext/search_tweaks/query_relevance/plugin.py
ckanext/search_tweaks/query_relevance/score.py
ckanext/search_tweaks/query_relevance/storage.py
ckanext/search_tweaks/spellcheck/__init__.py
ckanext/search_tweaks/spellcheck/cli.py
ckanext_search_tweaks-1.0.0.dist-info/licenses/LICENSE
ckanext_search_tweaks-1.0.0.dist-info/METADATA
ckanext_search_tweaks-1.0.0.dist-info/WHEEL
ckanext_search_tweaks-1.0.0.dist-info/entry_points.txt
ckanext_search_tweaks-1.0.0.dist-info/top_level.txt
ckanext_search_tweaks-1.0.0.dist-info/RECORD
