Metadata-Version: 2.4
Name: ckanext-search-tweaks
Version: 1.0.0
Author-email: DataShades <datashades@linkdigital.com.au>, Sergey Motornyuk <sergey.motornyuk@linkdigital.com.au>
Maintainer-email: DataShades <datashades@linkdigital.com.au>
License: AGPL
Project-URL: Homepage, https://github.com/DataShades/ckanext-search-tweaks
Keywords: CKAN
Classifier: Development Status :: 4 - Beta
Classifier: License :: OSI Approved :: GNU Affero General Public License v3 or later (AGPLv3+)
Classifier: Programming Language :: Python :: 3.10
Classifier: Programming Language :: Python :: 3.11
Classifier: Programming Language :: Python :: 3.12
License-File: LICENSE
Requires-Dist: freezegun
Requires-Dist: typing_extensions>=4.0.0
Requires-Dist: ckanext-toolbelt>=0.6.6
Provides-Extra: dev
Requires-Dist: pytest-ckan; extra == "dev"
Requires-Dist: pytest-freezegun; extra == "dev"
Requires-Dist: pytest-factoryboy; extra == "dev"
Requires-Dist: pytest-rerunfailures; extra == "dev"
Dynamic: license-file
